CHANGELOG
MANIFEST.in
README.md
requirements.txt
setup.cfg
setup.py
versioneer.py
src/ProcessCDB/_version.py
src/processcdb/__init__.py
src/processcdb/__main__.py
src/processcdb/_version.py
src/processcdb/cdb_tools.py
src/processcdb/clang.py
src/processcdb/clangtidy.py
src/processcdb/cppcheck.py
src/processcdb/lizard.py
src/processcdb/logger.py
src/processcdb/misc.py
src/processcdb/tidy_converter.py
src/processcdb/toolbase.py
src/processcdb.egg-info/PKG-INFO
src/processcdb.egg-info/SOURCES.txt
src/processcdb.egg-info/dependency_links.txt
src/processcdb.egg-info/entry_points.txt
src/processcdb.egg-info/requires.txt
src/processcdb.egg-info/top_level.txt