Metadata-Version: 2.1
Name: processcdb
Version: 0.1.10
Summary: Front-end to process compile_commands.json file and run various static analysis tools against it
Home-page: https://github.com/rasjani/processcdb
Author: Jani Mikkonen
Author-email: jani.mikkonen@gmail.com
License: Apache License 2.0
Keywords: staticanalysis frontend clang cppcheck clangtidy compile_commands.json
Platform: any
Classifier: Development Status :: 3 - Alpha
Classifier: Topic :: Software Development :: Testing
Classifier: Operating System :: OS Independent
Classifier: License :: OSI Approved :: Apache Software License
Classifier: Programming Language :: Python
Classifier: Programming Language :: Python :: 3
Classifier: Programming Language :: Python :: 3.7
Classifier: Programming Language :: Python :: 3.8
Classifier: Programming Language :: Python :: 3.9
Classifier: Topic :: Software Development :: Testing
